fzz_tunes/__init__.py
fzz_tunes/__main__.py
fzz_tunes/configs.py
fzz_tunes/core.py
fzz_tunes/main.py
fzz_tunes/os_compatibility.py
fzz_tunes/search_youtube.py
fzz_tunes/user_input.py
fzz_tunes/windows.py
fzz_tunes-0.1.5.dist-info/entry_points.txt
fzz_tunes-0.1.5.dist-info/METADATA
fzz_tunes-0.1.5.dist-info/WHEEL
fzz_tunes-0.1.5.dist-info/RECORD
